remotecv/__init__.py
remotecv/celery_tasks.py
remotecv/error_handler.py
remotecv/healthcheck.py
remotecv/http_loader.py
remotecv/image.py
remotecv/image_processor.py
remotecv/importer.py
remotecv/pyres_tasks.py
remotecv/timing.py
remotecv/unique_queue.py
remotecv/utils.py
remotecv/worker.py
remotecv/detectors/__init__.py
remotecv/detectors/complete_detector/__init__.py
remotecv/detectors/face_detector/__init__.py
remotecv/detectors/face_detector/haarcascade_frontalface_alt.xml
remotecv/detectors/face_detector/haarcascade_frontalface_alt2.xml
remotecv/detectors/face_detector/haarcascade_frontalface_alt_tree.xml
remotecv/detectors/face_detector/haarcascade_frontalface_default.xml
remotecv/detectors/feature_detector/__init__.py
remotecv/detectors/glasses_detector/__init__.py
remotecv/detectors/glasses_detector/haarcascade_eye_tree_eyeglasses.xml
remotecv/detectors/profile_detector/__init__.py
remotecv/detectors/profile_detector/haarcascade_profileface.xml
remotecv/metrics/__init__.py
remotecv/metrics/logger_metrics.py
remotecv/result_store/__init__.py
remotecv/result_store/memcache_store.py
remotecv/result_store/redis_store.py
remotecv-5.1.9.dist-info/LICENSE
remotecv-5.1.9.dist-info/METADATA
remotecv-5.1.9.dist-info/WHEEL
remotecv-5.1.9.dist-info/entry_points.txt
remotecv-5.1.9.dist-info/top_level.txt
remotecv-5.1.9.dist-info/RECORD
