Metadata-Version: 2.1
Name: remotecv
Version: 5.1.9
Summary: remotecv is an OpenCV worker for facial and feature recognition
Home-page: https://github.com/thumbor/remotecv
Author: Bernardo Heynemann
Author-email: heynemann@gmail.com
License: MIT
Classifier: Development Status :: 4 - Beta
Classifier: Intended Audience :: Developers
Classifier: License :: OSI Approved :: MIT License
Classifier: Natural Language :: English
Classifier: Operating System :: MacOS
Classifier: Operating System :: POSIX :: Linux
Classifier: Programming Language :: Python :: 3
Classifier: Programming Language :: Python :: 3.9
Classifier: Programming Language :: Python :: 3.10
Classifier: Programming Language :: Python :: 3.11
Classifier: Programming Language :: Python :: 3.12
Classifier: Programming Language :: Python :: 3 :: Only
Classifier: Topic :: Internet :: WWW/HTTP :: Dynamic Content
Classifier: Topic :: Multimedia :: Graphics :: Presentation
Requires-Python: ==3.*,>=3.9.0
License-File: LICENSE
Requires-Dist: opencv-python-headless==4.*,>=4.9.0.80
Requires-Dist: Pillow==10.*
Requires-Dist: pyres==1.*,>=1.5
Requires-Dist: redis==5.0.1
Requires-Dist: sentry-sdk==1.*,>=1.39.1
Requires-Dist: click==8.*,>=8.1.7
Requires-Dist: click-option-group==0.*,>=0.5.6
Provides-Extra: dev
Requires-Dist: opencv-python-headless==4.*,>=4.9.0.80; extra == "dev"
Requires-Dist: Pillow==10.*; extra == "dev"
Requires-Dist: pyres==1.*,>=1.5; extra == "dev"
Requires-Dist: redis==5.0.1; extra == "dev"
Requires-Dist: sentry-sdk==1.*,>=1.39.1; extra == "dev"
Requires-Dist: click==8.*,>=8.1.7; extra == "dev"
Requires-Dist: click-option-group==0.*,>=0.5.6; extra == "dev"
Requires-Dist: black==23.*,>=23.12.1; extra == "dev"
Requires-Dist: celery==5.*,>=5.3.6; extra == "dev"
Requires-Dist: coverage==7.*,>=7.4.0; extra == "dev"
Requires-Dist: flake8==7.*,>=7.0.0; extra == "dev"
Requires-Dist: numpy<2.0.0,>=1.26.4; extra == "dev"
Requires-Dist: pre-commit==3.*,>=3.6.0; extra == "dev"
Requires-Dist: preggy==1.*,>=1.4.4; extra == "dev"
Requires-Dist: pylint==3.*,>=3.0.3; extra == "dev"
Requires-Dist: pyssim==0.*,>=0.7; extra == "dev"
Requires-Dist: pytest-asyncio==0.*,>=0.23.0; extra == "dev"
Requires-Dist: pytest-cov==4.*,>=4.1.0; extra == "dev"
Requires-Dist: pytest==7.*,>=7.4.0; extra == "dev"
Requires-Dist: thumbor==7.*,>=7.7.5; extra == "dev"
